pyplugs/__init__.py
pyplugs/_exceptions.py
pyplugs/_plugins.py
pyplugs/py.typed
pyplugs-0.5.4.dist-info/licenses/LICENSE
pyplugs-0.5.4.dist-info/METADATA
pyplugs-0.5.4.dist-info/WHEEL
pyplugs-0.5.4.dist-info/top_level.txt
pyplugs-0.5.4.dist-info/RECORD
