Metadata-Version: 2.4
Name: pyplugs
Version: 0.5.4
Summary: PyPlugs, decorator based plug-in architecture for Python
Author-email: Geir Arne Hjelle <geirarne@gmail.com>
License-Expression: MIT
Project-URL: Home, https://github.com/gahjelle/pyplugs
Keywords: plugin,decorator
Classifier: Development Status :: 5 - Production/Stable
Classifier: Intended Audience :: Developers
Classifier: Natural Language :: English
Classifier: Operating System :: OS Independent
Classifier: Programming Language :: Python :: 3.10
Classifier: Programming Language :: Python :: 3.11
Classifier: Programming Language :: Python :: 3.12
Classifier: Programming Language :: Python :: 3.13
Classifier: Programming Language :: Python :: 3.14
Classifier: Topic :: Software Development :: Libraries :: Python Modules
Requires-Python: >=3.10
License-File: LICENSE
Dynamic: license-file
